precon/__init__.py
precon/_validation.py
precon/adjustments.py
precon/aggregation.py
precon/chaining.py
precon/contributions.py
precon/double_update_methods.py
precon/enums.py
precon/helpers.py
precon/imputation.py
precon/index_methods.py
precon/oohtree.py
precon/pipelines.py
precon/re_reference.py
precon/rounding.py
precon/stat_compilers.py
precon/tree.py
precon/uprate.py
precon/weights.py
precon-0.6.2.dist-info/AUTHORS.rst
precon-0.6.2.dist-info/LICENSE
precon-0.6.2.dist-info/METADATA
precon-0.6.2.dist-info/WHEEL
precon-0.6.2.dist-info/top_level.txt
precon-0.6.2.dist-info/RECORD
