Metadata-Version: 2.1
Name: precon
Version: 0.6.2
Summary: A set of functions to calculate Prices Economics statistics.
Home-page: https://github.com/ONSBigData/precon
Author: Mitchell Edmunds
Author-email: mitchell.edmunds@ext.ons.gov.uk
License: MIT
Keywords: precon
Platform: UNKNOWN
Classifier: Development Status :: 2 - Pre-Alpha
Classifier: Intended Audience :: Developers
Classifier: License :: OSI Approved :: MIT License
Classifier: Natural Language :: English
Classifier: Programming Language :: Python :: 3.6
Classifier: Programming Language :: Python :: 3.8
Classifier: Programming Language :: Python :: 3.9
Classifier: Programming Language :: Python :: Implementation :: PyPy
Requires-Dist: pandas
Requires-Dist: numpy
